mdu_snpit/__init__.py
mdu_snpit/main.py
mdu_snpit/db/snpit.count.json
mdu_snpit/db/snpit.db.json
mdu_snpit/db/snpit.id.json
mdu_snpit-0.1.0.dist-info/METADATA
mdu_snpit-0.1.0.dist-info/WHEEL
mdu_snpit-0.1.0.dist-info/entry_points.txt
mdu_snpit-0.1.0.dist-info/top_level.txt
mdu_snpit-0.1.0.dist-info/RECORD
